pipus/__init__.py
pipus/__main__.py
pipus/args.py
pipus-1.3.dist-info/LICENSE
pipus-1.3.dist-info/METADATA
pipus-1.3.dist-info/WHEEL
pipus-1.3.dist-info/entry_points.txt
pipus-1.3.dist-info/top_level.txt
pipus-1.3.dist-info/RECORD
