Metadata-Version: 2.1
Name: pipus
Version: 1.3
Home-page: https://github.com/Tina-otoge/pipus
License-File: LICENSE
